glimpse/__init__.py
glimpse/config.py
glimpse/policy.py
glimpse/tracer.py
glimpse/common/__init__.py
glimpse/common/ids.py
glimpse/writers/base.py
glimpse/writers/json.py
glimpse/writers/logentry.py
glimpse/writers/logwriter.py
glimpse/writers/sqlite.py
glimpse_py-0.1.0.dist-info/METADATA
glimpse_py-0.1.0.dist-info/WHEEL
glimpse_py-0.1.0.dist-info/top_level.txt
glimpse_py-0.1.0.dist-info/RECORD
