Metadata-Version: 2.4
Name: glimpse-py
Version: 0.1.0
Summary: Trace, analyze, and monitor Python application execution with configurable policies and multiple output formats.
Author-email: pxpatel <pxpatel04@gmail.com>
License: MIT
Project-URL: Homepage, https://github.com/PxPatel/glimpse
Project-URL: Repository, https://github.com/PxPatel/glimpse
Keywords: tracing,debugging,monitoring,profiling,python
Classifier: Development Status :: 3 - Alpha
Classifier: Intended Audience :: Developers
Classifier: Topic :: Software Development :: Debuggers
Classifier: Topic :: System :: Monitoring
Classifier: Programming Language :: Python :: 3
Classifier: Programming Language :: Python :: 3.7
Classifier: Programming Language :: Python :: 3.8
Classifier: Programming Language :: Python :: 3.9
Classifier: Programming Language :: Python :: 3.10
Classifier: Programming Language :: Python :: 3.11
Classifier: Programming Language :: Python :: 3.12
Classifier: License :: OSI Approved :: MIT License
Classifier: Operating System :: OS Independent
Requires-Python: >=3.7
Requires-Dist: colorama>=0.4.6
Requires-Dist: python-dotenv>=1.1.1
Requires-Dist: Pygments>=2.19.2
Provides-Extra: dev
Requires-Dist: pytest>=8.4.1; extra == "dev"
